rpc_viewer/__init__.py
rpc_viewer/rpc_viewer.py
rpc_viewer-0.4.dist-info/LICENSE
rpc_viewer-0.4.dist-info/METADATA
rpc_viewer-0.4.dist-info/WHEEL
rpc_viewer-0.4.dist-info/entry_points.txt
rpc_viewer-0.4.dist-info/top_level.txt
rpc_viewer-0.4.dist-info/RECORD
