Metadata-Version: 2.1
Name: rpc-viewer
Version: 0.4
Summary: Application to visualize MTS PRC3 files
Home-page: https://gitlab.com/t8237/rpc_viewer
Author: Lukas Stockmann
Author-email: lukas.stockmann@t-online.de
License: UNKNOWN
Platform: UNKNOWN
Classifier: Development Status :: 4 - Beta
Classifier: Programming Language :: Python :: 3
Classifier: License :: OSI Approved :: MIT License
Classifier: Operating System :: OS Independent
Requires-Python: >=3.7
License-File: LICENSE
Requires-Dist: setuptools
Requires-Dist: wheel
Requires-Dist: numpy
Requires-Dist: matplotlib
Requires-Dist: rpc-reader
